tei_client/__about__.py
tei_client/__init__.py
tei_client/models.py
tei_client/clients/base.py
tei_client/clients/grpc_client.py
tei_client/clients/http_client.py
tei_client/stubs/__init__.py
tei_client/stubs/tei_pb2.py
tei_client/stubs/tei_pb2.pyi
tei_client/stubs/tei_pb2_grpc.py
tei_client-0.2.4.dist-info/METADATA
tei_client-0.2.4.dist-info/WHEEL
tei_client-0.2.4.dist-info/licenses/LICENSE
tei_client-0.2.4.dist-info/RECORD
