Metadata-Version: 2.4
Name: tei-client
Version: 0.2.4
Summary: Convenience Client for Hugging Face Text Embeddings Inference (TEI) with synchronous and asynchronous HTTP/gRPC support
Project-URL: Documentation, https://github.com/LLukas22/tei-client#readme
Project-URL: Issues, https://github.com/LLukas22/tei-client/issues
Project-URL: Source, https://github.com/LLukas22/tei-client
Author-email: Lukas Kreussel <65088241+LLukas22@users.noreply.github.com>
License-Expression: MIT
License-File: LICENSE
Classifier: Development Status :: 4 - Beta
Classifier: Programming Language :: Python
Classifier: Programming Language :: Python :: 3.9
Classifier: Programming Language :: Python :: 3.10
Classifier: Programming Language :: Python :: 3.11
Classifier: Programming Language :: Python :: 3.12
Classifier: Programming Language :: Python :: Implementation :: CPython
Classifier: Programming Language :: Python :: Implementation :: PyPy
Requires-Python: >=3.9
Requires-Dist: httpx>=0.20
Requires-Dist: pydantic>=2.0
Provides-Extra: grpc
Requires-Dist: grpcio>=1.60.0; extra == 'grpc'
Requires-Dist: protobuf; extra == 'grpc'
Provides-Extra: testing
Requires-Dist: pytest; extra == 'testing'
Requires-Dist: pytest-asyncio; extra == 'testing'
